sphere/core/schemas/abstract_raster_reader.py
sphere/core/schemas/abstract_vulnerability_function.py
sphere/core/schemas/base_vulnerability_function.py
sphere/core/schemas/buildings.py
sphere/core/schemas/buildings_field_names.py
sphere/core/schemas/fast_buildings.py
sphere/core/schemas/field_mapping.py
sphere/core/schemas/nsi_buildings.py
sphere_core-0.2.0.dist-info/WHEEL
sphere_core-0.2.0.dist-info/entry_points.txt
sphere_core-0.2.0.dist-info/METADATA
sphere_core-0.2.0.dist-info/RECORD
