Metadata-Version: 2.3
Name: sphere-core
Version: 0.2.0
Summary: Add your description here
Author: Troy Schmidt
Author-email: Troy Schmidt <tschmidt@niyamit.com>
Requires-Dist: geopandas>=1.1.1
Requires-Python: >=3.10
